vonage/__init__.py
vonage/_version.py
vonage/vonage.py
vonage-4.7.2.dist-info/METADATA
vonage-4.7.2.dist-info/WHEEL
vonage-4.7.2.dist-info/top_level.txt
vonage-4.7.2.dist-info/RECORD
