Metadata-Version: 2.4
Name: vonage
Version: 4.7.2
Summary: Python Server SDK for using Vonage APIs
Author-email: Vonage <devrel@vonage.com>
Project-URL: homepage, https://github.com/Vonage/vonage-python-sdk
Classifier: Programming Language :: Python
Classifier: Programming Language :: Python :: 3
Classifier: Programming Language :: Python :: 3.9
Classifier: Programming Language :: Python :: 3.10
Classifier: Programming Language :: Python :: 3.11
Classifier: Programming Language :: Python :: 3.12
Classifier: Programming Language :: Python :: 3.13
Classifier: License :: OSI Approved :: Apache Software License
Requires-Python: >=3.9
Requires-Dist: vonage-account>=1.1.1
Requires-Dist: vonage-application>=2.0.1
Requires-Dist: vonage-http-client>=1.5.1
Requires-Dist: vonage-messages>=1.5.0
Requires-Dist: vonage-network-auth>=1.0.2
Requires-Dist: vonage-network-sim-swap>=1.1.2
Requires-Dist: vonage-network-number-verification>=1.0.2
Requires-Dist: vonage-number-insight>=1.0.7
Requires-Dist: vonage-numbers>=1.0.4
Requires-Dist: vonage-sms>=1.1.6
Requires-Dist: vonage-subaccounts>=1.0.4
Requires-Dist: vonage-users>=1.2.1
Requires-Dist: vonage-utils>=1.1.4
Requires-Dist: vonage-verify>=2.1.0
Requires-Dist: vonage-verify-legacy>=1.0.1
Requires-Dist: vonage-video>=1.2.0
Requires-Dist: vonage-voice>=1.4.0
